artilipy/__init__.py
artilipy/addons.py
artilipy/client.py
artilipy/exceptions.py
artilipy-0.0.5.dist-info/LICENSE
artilipy-0.0.5.dist-info/METADATA
artilipy-0.0.5.dist-info/WHEEL
artilipy-0.0.5.dist-info/top_level.txt
artilipy-0.0.5.dist-info/RECORD
