Metadata-Version: 2.1
Name: artilipy
Version: 0.0.5
Summary: Official Python API wrapper for Artilities
Home-page: https://github.com/artilities/artilipy
Author: Artilities Team
Author-email: artilities@yandex.ru
Classifier: Programming Language :: Python :: 3
Classifier: License :: OSI Approved :: MIT License
Classifier: Operating System :: OS Independent
Requires-Python: >=3.6
License-File: LICENSE
